wmm/__init__.py
wmm/build.py
wmm/load.py
wmm/uncertainty.py
wmm/utils.py
wmm/coefs/WMM.COF
wmm_calculator-1.4.3.dist-info/licenses/LICENSE
wmm_calculator-1.4.3.dist-info/METADATA
wmm_calculator-1.4.3.dist-info/WHEEL
wmm_calculator-1.4.3.dist-info/top_level.txt
wmm_calculator-1.4.3.dist-info/RECORD
